tests/__init__.py
tests/test_client.py
wordpress_client/__init__.py
wordpress_client/client.py
wordpress_client/utils.py
wordpress_client-0.1.6.dist-info/METADATA
wordpress_client-0.1.6.dist-info/WHEEL
wordpress_client-0.1.6.dist-info/top_level.txt
wordpress_client-0.1.6.dist-info/RECORD
