Metadata-Version: 2.2
Name: wordpress-client
Version: 0.1.6
Summary: A Python client for interacting with WordPress REST API
Home-page: https://github.com/berkbirkan/wordpress-client
Author: Berk Birkan
Author-email: info@berkbirkan.com
Classifier: Programming Language :: Python :: 3
Classifier: License :: OSI Approved :: MIT License
Classifier: Operating System :: OS Independent
Requires-Python: >=3.6
Requires-Dist: requests
Dynamic: author
Dynamic: author-email
Dynamic: classifier
Dynamic: description
Dynamic: description-content-type
Dynamic: home-page
Dynamic: requires-dist
Dynamic: requires-python
Dynamic: summary
